elenchos_check_mymaria_replication/CheckMyMariaReplicationCommand.py
elenchos_check_mymaria_replication/DataLayer.py
elenchos_check_mymaria_replication/MyMariaReplicationPlugin.py
elenchos_check_mymaria_replication/__init__.py
elenchos_check_mymaria_replication/commands.xml
elenchos_check_mymaria_replication-1.4.0.dist-info/LICENSE.md
elenchos_check_mymaria_replication-1.4.0.dist-info/METADATA
elenchos_check_mymaria_replication-1.4.0.dist-info/WHEEL
elenchos_check_mymaria_replication-1.4.0.dist-info/RECORD
