Metadata-Version: 2.3
Name: elenchos_check_mymaria_replication
Version: 1.4.0
Summary: Élenchos: Check MySQL and MariaDB Replication
License: MIT
Keywords: Élenchos,Elenchos,MySQL,MariaDB,Replication
Author: Set Based IT Consultancy
Author-email: info@setbased.nl
Requires-Python: >=3.12.0,<4.0.0
Classifier: Development Status :: 5 - Production/Stable
Classifier: Intended Audience :: System Administrators
Classifier: License :: OSI Approved :: MIT License
Classifier: Programming Language :: Python :: 3
Classifier: Programming Language :: Python :: 3.12
Classifier: Programming Language :: Python :: 3.13
Classifier: Topic :: System :: Systems Administration
Requires-Dist: elenchos (>=1.2.0,<2.0.0)
Requires-Dist: mysql-connector-python (>=9.3.0,<10.0.0)
Project-URL: Documentation, https://github.com/NagiosElenchos/check_mymaria_replication
Project-URL: Repository, https://github.com/NagiosElenchos/check_mymaria_replication
